    <rule category="POWER">
		<category name="SUP"/>
		<category name="DIGIT"/>
    </rule>
    <rule category="SUP_SYMB_OR_BRACED_EXP">
		<category name="SUP"/>
		<category name="SYMB_OR_BRACED_EXP"/>
    </rule>
    <rule category="SUP_FRACTION">
		<category name="SUP"/>
		<category name="FRACTION"/>
    </rule>
    
    <rule category="SUB_SYMB_OR_BRACED_EXP">
		<category name="SUB"/>
		<category name="SYMB_OR_BRACED_EXP"/>		
    </rule>
    <rule category="SUB_SUBSERIES">
		<category name="SUB"/>
		<category name="SUBSERIES"/>
    </rule>
    <rule category="SUB_SUBLIMIT">
		<category name="SUB"/>
		<category name="SUBLIMIT"/>
    </rule>
    <rule category="SUB_EXP_LIST">
		<category name="SUB"/>
		<category name="MUTE_LBRACE"/>
		<category name="EXP_LIST"/>
		<category name="MUTE_RBRACE"/>
    </rule>